Metadata-Version: 2.4
Name: pycatsearch
Version: 5.2.2.4
Summary: Yet another implementation of JPL and CDMS spectroscopy catalogs offline search
Author-email: StSav012 <stsav012@gmail.com>
License: LGPL-3.0-only
Project-URL: Source Code, https://github.com/StSav012/pycatsearch
Project-URL: Bug Tracker, https://github.com/StSav012/pycatsearch/issues
Classifier: Development Status :: 5 - Production/Stable
Classifier: Environment :: Win32 (MS Windows)
Classifier: Environment :: X11 Applications :: Qt
Classifier: Intended Audience :: Science/Research
Classifier: License :: OSI Approved :: GNU Lesser General Public License v3 (LGPLv3)
Classifier: Operating System :: Microsoft :: Windows :: Windows 7
Classifier: Operating System :: Microsoft :: Windows :: Windows 8
Classifier: Operating System :: Microsoft :: Windows :: Windows 10
Classifier: Operating System :: Microsoft :: Windows :: Windows 11
Classifier: Operating System :: POSIX
Classifier: Programming Language :: Python :: 3.8
Classifier: Programming Language :: Python :: 3.9
Classifier: Programming Language :: Python :: 3.10
Classifier: Programming Language :: Python :: 3.11
Classifier: Programming Language :: Python :: 3.12
Classifier: Topic :: Scientific/Engineering
Classifier: Topic :: Scientific/Engineering :: Astronomy
Classifier: Topic :: Scientific/Engineering :: Atmospheric Science
Classifier: Topic :: Scientific/Engineering :: Chemistry
Classifier: Topic :: Scientific/Engineering :: Physics
Classifier: Typing :: Typed
Requires-Python: >=3.8
License-File: LICENSE.md
Requires-Dist: PySide6-Essentials!=6.8.0,!=6.8.0.1,>=6.2.0
Requires-Dist: qtpy>=2.4.1
Dynamic: license-file
Dynamic: requires-dist
